pygpulab/__init__.py
pygpulab/__main__.py
pygpulab/main.py
pygpulab-0.1.0.dist-info/LICENSE
pygpulab-0.1.0.dist-info/METADATA
pygpulab-0.1.0.dist-info/WHEEL
pygpulab-0.1.0.dist-info/entry_points.txt
pygpulab-0.1.0.dist-info/top_level.txt
pygpulab-0.1.0.dist-info/RECORD
